[
    {
        "ID": false,
        "key": "group_ll2nrhvrxktnw",
        "title": "Page Home",
        "fields": [
            {
                "key": "field_ci1djlwhi5ox1",
                "label": "Intro",
                "name": "",
                "aria-label": "",
                "type": "tab",
                "instructions": "",
                "required": 0,
                "conditional_logic": 0,
                "wrapper": {
                    "width": "",
                    "class": "",
                    "id": ""
                },
                "placement": "top",
                "endpoint": 0
            },
            {
                "key": "field_vwcv0ex9lmzgr",
                "label": "Intro",
                "name": "intro",
                "aria-label": "",
                "type": "group",
                "instructions": "",
                "required": 0,
                "conditional_logic": 0,
                "wrapper": {
                    "width": "",
                    "class": "",
                    "id": ""
                },
                "layout": "row",
                "sub_fields": [
                    {
                        "key": "field_hor7u0relyfof",
                        "label": "Title",
                        "name": "title",
                        "aria-label": "",
                        "type": "text",
                        "instructions": "",
                        "required": 0,
                        "conditional_logic": 0,
                        "wrapper": {
                            "width": "30",
                            "class": "",
                            "id": ""
                        },
                        "default_value": "",
                        "maxlength": "",
                        "placeholder": "",
                        "prepend": "",
                        "append": ""
                    },
                    {
                        "key": "field_l04gt0aysilp6",
                        "label": "Textarea",
                        "name": "textarea",
                        "aria-label": "",
                        "type": "text",
                        "instructions": "",
                        "required": 0,
                        "conditional_logic": 0,
                        "wrapper": {
                            "width": "100",
                            "class": "",
                            "id": ""
                        },
                        "default_value": "",
                        "maxlength": "",
                        "placeholder": "",
                        "prepend": "",
                        "append": ""
                    },
                    {
                        "key": "field_1adpos6oflzub",
                        "label": "Text",
                        "name": "text",
                        "aria-label": "",
                        "type": "wysiwyg",
                        "instructions": "",
                        "required": 0,
                        "conditional_logic": 0,
                        "wrapper": {
                            "width": "100",
                            "class": "",
                            "id": ""
                        },
                        "default_value": "",
                        "maxlength": "",
                        "placeholder": "",
                        "prepend": "",
                        "append": "",
                        "toolbar": "basic",
                        "media_upload": 0,
                        "tabs": "all",
                        "delay": 0
                    },
                    {
                        "key": "field_c1m6yakfdft0a",
                        "label": "Image",
                        "name": "image",
                        "aria-label": "",
                        "type": "image",
                        "instructions": "",
                        "required": 0,
                        "conditional_logic": 0,
                        "wrapper": {
                            "width": "100",
                            "class": "",
                            "id": ""
                        },
                        "default_value": "",
                        "maxlength": "",
                        "placeholder": "",
                        "prepend": "",
                        "append": "",
                        "return_format": "array",
                        "preview_size": "thumbnail",
                        "library": "all",
                        "min_width": 0,
                        "min_height": 0,
                        "min_size": 0,
                        "max_width": 0,
                        "max_height": 0,
                        "max_size": 0,
                        "mime_types": ""
                    },
                    {
                        "key": "field_2lzhempzsybo4",
                        "label": "Gallery",
                        "name": "gallery",
                        "aria-label": "",
                        "type": "gallery",
                        "instructions": "",
                        "required": 0,
                        "conditional_logic": 0,
                        "wrapper": {
                            "width": "100",
                            "class": "",
                            "id": ""
                        },
                        "default_value": "",
                        "maxlength": "",
                        "placeholder": "",
                        "prepend": "",
                        "append": "",
                        "return_format": "array",
                        "preview_size": "thumbnail",
                        "insert": "append",
                        "library": "all",
                        "min": 0,
                        "max": 0,
                        "min_width": 0,
                        "min_height": 0,
                        "min_size": 0,
                        "max_width": 0,
                        "max_height": 0,
                        "max_size": 0,
                        "mime_types": ""
                    },
                    {
                        "key": "field_gd7b78irij8r9",
                        "label": "Label",
                        "name": "label",
                        "aria-label": "",
                        "type": "text",
                        "instructions": "",
                        "required": true,
                        "conditional_logic": 0,
                        "wrapper": {
                            "width": 50,
                            "class": "",
                            "id": ""
                        },
                        "default_value": "",
                        "maxlength": "",
                        "placeholder": "",
                        "prepend": "",
                        "append": ""
                    },
                    {
                        "key": "field_lsok2i6nm0cvo",
                        "label": "Repeater",
                        "name": "repeater",
                        "aria-label": "",
                        "type": "repeater",
                        "instructions": "",
                        "required": 0,
                        "conditional_logic": 0,
                        "wrapper": {
                            "width": "100",
                            "class": "",
                            "id": ""
                        },
                        "default_value": "",
                        "maxlength": "",
                        "placeholder": "",
                        "prepend": "",
                        "append": "",
                        "layout": "block",
                        "button_label": "Add Row",
                        "min": 0,
                        "max": 0,
                        "rows_per_page": 20,
                        "collapsed": "",
                        "sub_fields": [
                            {
                                "key": "field_ipljwpnjd3wat",
                                "label": "Test",
                                "name": "test",
                                "aria-label": "",
                                "type": "text",
                                "instructions": "",
                                "required": true,
                                "conditional_logic": 0,
                                "wrapper": {
                                    "width": 40,
                                    "class": "",
                                    "id": ""
                                },
                                "default_value": "",
                                "maxlength": "",
                                "placeholder": "",
                                "prepend": "",
                                "append": "",
                                "parent_repeater": "field_lsok2i6nm0cvo"
                            }
                        ]
                    },
                    {
                        "key": "field_w575fae2u8rkg",
                        "label": "Message",
                        "name": "",
                        "aria-label": "",
                        "type": "message",
                        "instructions": "",
                        "required": 0,
                        "conditional_logic": 0,
                        "wrapper": {
                            "width": "100",
                            "class": "",
                            "id": ""
                        },
                        "default_value": "",
                        "maxlength": "",
                        "placeholder": "",
                        "prepend": "",
                        "append": "",
                        "message": "",
                        "esc_html": 0,
                        "new_lines": "wpautop"
                    },
                    {
                        "key": "field_3svjxfxq4a1yk",
                        "label": "TrueFalse",
                        "name": "truefalse",
                        "aria-label": "",
                        "type": "true_false",
                        "instructions": "",
                        "required": 0,
                        "conditional_logic": 0,
                        "wrapper": {
                            "width": "100",
                            "class": "",
                            "id": ""
                        },
                        "default_value": "",
                        "maxlength": "",
                        "placeholder": "",
                        "prepend": "",
                        "append": "",
                        "ui": 1,
                        "message": "",
                        "ui_on_text": "",
                        "ui_off_text": ""
                    }
                ]
            },
            {
                "key": "field_of8zby1tb7bhe",
                "label": "About",
                "name": "",
                "aria-label": "",
                "type": "tab",
                "instructions": "",
                "required": 0,
                "conditional_logic": 0,
                "wrapper": {
                    "width": "",
                    "class": "",
                    "id": ""
                },
                "placement": "top",
                "endpoint": 0
            },
            {
                "key": "field_ggqp2eaxwd4ek",
                "label": "About",
                "name": "about",
                "aria-label": "",
                "type": "group",
                "instructions": "",
                "required": 0,
                "conditional_logic": 0,
                "wrapper": {
                    "width": "",
                    "class": "",
                    "id": ""
                },
                "layout": "row",
                "sub_fields": [
                    {
                        "key": "field_q3zfbi4qfxwkx",
                        "label": "Title",
                        "name": "title",
                        "aria-label": "",
                        "type": "text",
                        "instructions": "",
                        "required": 0,
                        "conditional_logic": 0,
                        "wrapper": {
                            "width": "40",
                            "class": "",
                            "id": ""
                        },
                        "default_value": "",
                        "maxlength": "",
                        "placeholder": "",
                        "prepend": "",
                        "append": ""
                    },
                    {
                        "key": "field_6t2jazrfi6xvj",
                        "label": "Text",
                        "name": "text",
                        "aria-label": "",
                        "type": "wysiwyg",
                        "instructions": "",
                        "required": true,
                        "conditional_logic": 0,
                        "wrapper": {
                            "width": 50,
                            "class": "",
                            "id": ""
                        },
                        "tabs": "all",
                        "toolbar": "full",
                        "media_upload": 1,
                        "default_value": "",
                        "delay": 0
                    },
                    {
                        "key": "field_pwr8w5pq4qbhd",
                        "label": "File",
                        "name": "file",
                        "aria-label": "",
                        "type": "file",
                        "instructions": "",
                        "required": 0,
                        "conditional_logic": 0,
                        "wrapper": {
                            "width": "50",
                            "class": "",
                            "id": ""
                        },
                        "default_value": "",
                        "maxlength": "",
                        "placeholder": "",
                        "prepend": "",
                        "append": "",
                        "return_format": "array",
                        "preview_size": "thumbnail",
                        "library": "all",
                        "min_size": 0,
                        "max_size": 0,
                        "mime_types": ""
                    }
                ]
            },
            {
                "key": "field_ctkiyepntluzq",
                "label": "Features",
                "name": "",
                "aria-label": "",
                "type": "tab",
                "instructions": "",
                "required": 0,
                "conditional_logic": 0,
                "wrapper": {
                    "width": 100,
                    "class": "",
                    "id": ""
                },
                "message": "",
                "placement": "top",
                "endpoint": 0
            },
            {
                "key": "field_tvpdkathtg8gi",
                "label": "Features",
                "name": "features",
                "aria-label": "",
                "type": "group",
                "instructions": "",
                "required": false,
                "conditional_logic": 0,
                "wrapper": {
                    "width": 100,
                    "class": "",
                    "id": ""
                },
                "message": "",
                "layout": "row",
                "sub_fields": [
                    {
                        "key": "field_efuroqxcuiuof",
                        "label": "Label",
                        "name": "label",
                        "aria-label": "",
                        "type": "text",
                        "instructions": "",
                        "required": true,
                        "conditional_logic": 0,
                        "wrapper": {
                            "width": 30,
                            "class": "",
                            "id": ""
                        },
                        "default_value": "",
                        "maxlength": "",
                        "placeholder": "",
                        "prepend": "",
                        "append": ""
                    },
                    {
                        "key": "field_k2yyruj1nxmhr",
                        "label": "Message",
                        "name": "",
                        "aria-label": "",
                        "type": "message",
                        "instructions": "",
                        "required": 0,
                        "conditional_logic": 0,
                        "wrapper": {
                            "width": 100,
                            "class": "",
                            "id": ""
                        },
                        "message": "My new field",
                        "esc_html": 0,
                        "new_lines": "wpautop"
                    }
                ]
            }
        ],
        "location": [
            [
                {
                    "param": "page",
                    "operator": "==",
                    "value": "2"
                }
            ]
        ],
        "menu_order": 0,
        "position": "normal",
        "style": "default",
        "label_placement": "top",
        "instruction_placement": "label",
        "hide_on_screen": "",
        "active": true,
        "description": "",
        "show_in_rest": 0,
        "_valid": true
    }
]