[
    {
        "ID": false,
        "key": "group_vo5rn7cd6rwym",
        "title": "Reviews",
        "fields": [
            {
                "key": "field_hbddasjqw7jez",
                "label": "Reviews",
                "name": "",
                "aria-label": "",
                "type": "tab",
                "instructions": "",
                "required": 0,
                "conditional_logic": 0,
                "wrapper": {
                    "width": 100,
                    "class": "",
                    "id": ""
                },
                "message": "",
                "ui": 0,
                "default_value": 0,
                "placement": "top",
                "endpoint": 0,
                "no_preference": 0
            },
            {
                "key": "field_at0quxbkexdaw",
                "label": "Reviews",
                "name": "reviews",
                "aria-label": "",
                "type": "group",
                "instructions": "",
                "required": false,
                "conditional_logic": 0,
                "wrapper": {
                    "width": 100,
                    "class": "",
                    "id": ""
                },
                "message": "",
                "ui": 0,
                "default_value": 0,
                "layout": "block",
                "acfe_seamless_style": 0,
                "acfe_group_modal": 0,
                "acfe_group_modal_close": 0,
                "acfe_group_modal_button": "",
                "acfe_group_modal_size": "large",
                "sub_fields": [
                    {
                        "key": "field_6893701ef7d73",
                        "label": "Bg Color",
                        "name": "bg_color",
                        "aria-label": "",
                        "type": "select",
                        "instructions": "",
                        "required": 0,
                        "conditional_logic": 0,
                        "wrapper": {
                            "width": "33",
                            "class": "",
                            "id": ""
                        },
                        "choices": {
                            "default": "Default",
                            "alt": "Alt"
                        },
                        "default_value": false,
                        "return_format": "value",
                        "multiple": 0,
                        "allow_null": 0,
                        "ui": 0,
                        "ajax": 0,
                        "placeholder": "",
                        "allow_custom": 0,
                        "search_placeholder": "",
                        "prepend": "",
                        "append": "",
                        "min": "",
                        "max": ""
                    },
                    {
                        "key": "field_qr1unwpb3gpcg",
                        "label": "Tag",
                        "name": "tag",
                        "aria-label": "",
                        "type": "text",
                        "instructions": "",
                        "required": 1,
                        "conditional_logic": 0,
                        "wrapper": {
                            "width": "33",
                            "class": "",
                            "id": ""
                        },
                        "default_value": 0,
                        "maxlength": "",
                        "placeholder": "",
                        "prepend": "",
                        "append": ""
                    },
                    {
                        "key": "field_9fzmfw6hdtesj",
                        "label": "Title",
                        "name": "title",
                        "aria-label": "",
                        "type": "text",
                        "instructions": "",
                        "required": 1,
                        "conditional_logic": 0,
                        "wrapper": {
                            "width": "33",
                            "class": "",
                            "id": ""
                        },
                        "default_value": 0,
                        "maxlength": "",
                        "placeholder": "",
                        "prepend": "",
                        "append": ""
                    },
                    {
                        "key": "field_vsuacmds0dspx",
                        "label": "Body",
                        "name": "body",
                        "type": "repeater",
                        "instructions": "",
                        "required": false,
                        "conditional_logic": 0,
                        "wrapper": {
                            "width": 100,
                            "class": "",
                            "id": ""
                        },
                        "message": "",
                        "ui": 0,
                        "default_value": 0,
                        "sub_fields": [],
                        "layout": "block"
                    },
                    {
                        "key": "field_vgb0kd2ugwem8",
                        "label": "Items",
                        "name": "items",
                        "aria-label": "",
                        "type": "repeater",
                        "instructions": "",
                        "required": false,
                        "conditional_logic": 0,
                        "wrapper": {
                            "width": 100,
                            "class": "",
                            "id": ""
                        },
                        "message": "",
                        "ui": 0,
                        "default_value": 0,
                        "layout": "block",
                        "min": 0,
                        "max": 0,
                        "rows_per_page": 20,
                        "button_label": "Add Row",
                        "collapsed": "",
                        "acfe_repeater_stylised_button": 0,
                        "sub_fields": [
                            {
                                "key": "field_6895d963e0e3b",
                                "label": "Bg Card Color",
                                "name": "bg_card_color",
                                "aria-label": "",
                                "type": "select",
                                "instructions": "",
                                "required": 0,
                                "conditional_logic": 0,
                                "wrapper": {
                                    "width": "33",
                                    "class": "",
                                    "id": ""
                                },
                                "choices": {
                                    "default": "Default",
                                    "alt": "Alt"
                                },
                                "default_value": false,
                                "return_format": "value",
                                "multiple": 0,
                                "allow_null": 0,
                                "ui": 0,
                                "ajax": 0,
                                "placeholder": "",
                                "parent_repeater": "field_vgb0kd2ugwem8",
                                "allow_custom": 0,
                                "search_placeholder": "",
                                "prepend": "",
                                "append": "",
                                "min": "",
                                "max": ""
                            },
                            {
                                "key": "field_r3jz32rwpm6px",
                                "label": "Photo",
                                "name": "photo",
                                "aria-label": "",
                                "type": "image",
                                "instructions": "",
                                "required": 1,
                                "conditional_logic": 0,
                                "wrapper": {
                                    "width": "33",
                                    "class": "",
                                    "id": ""
                                },
                                "return_format": "array",
                                "library": "all",
                                "min_width": "",
                                "min_height": "",
                                "min_size": "",
                                "max_width": "",
                                "max_height": "",
                                "max_size": "",
                                "mime_types": "",
                                "preview_size": "medium",
                                "parent_repeater": "field_vgb0kd2ugwem8",
                                "uploader": "",
                                "acfe_thumbnail": 0,
                                "upload_folder": ""
                            },
                            {
                                "key": "field_p9cwdtpsiybxd",
                                "label": "Name",
                                "name": "name",
                                "aria-label": "",
                                "type": "text",
                                "instructions": "",
                                "required": 1,
                                "conditional_logic": 0,
                                "wrapper": {
                                    "width": "33",
                                    "class": "",
                                    "id": ""
                                },
                                "default_value": "",
                                "maxlength": "",
                                "placeholder": "",
                                "prepend": "",
                                "append": "",
                                "parent_repeater": "field_vgb0kd2ugwem8"
                            },
                            {
                                "key": "field_oacrxh21talkd",
                                "label": "Company",
                                "name": "company",
                                "aria-label": "",
                                "type": "text",
                                "instructions": "",
                                "required": 1,
                                "conditional_logic": 0,
                                "wrapper": {
                                    "width": "40",
                                    "class": "",
                                    "id": ""
                                },
                                "default_value": 0,
                                "maxlength": "",
                                "placeholder": "",
                                "prepend": "",
                                "append": "",
                                "parent_repeater": "field_vgb0kd2ugwem8"
                            },
                            {
                                "key": "field_l1ixnyzztfdbn",
                                "label": "Comment",
                                "name": "comment",
                                "aria-label": "",
                                "type": "textarea",
                                "instructions": "",
                                "required": 1,
                                "conditional_logic": 0,
                                "wrapper": {
                                    "width": "60",
                                    "class": "",
                                    "id": ""
                                },
                                "default_value": 0,
                                "maxlength": "",
                                "rows": "",
                                "placeholder": "",
                                "new_lines": "",
                                "parent_repeater": "field_vgb0kd2ugwem8",
                                "acfe_textarea_code": 0
                            },
                            {
                                "key": "field_6jw9yal9sevnt",
                                "label": "Stars",
                                "name": "stars",
                                "aria-label": "",
                                "type": "repeater",
                                "instructions": "",
                                "required": true,
                                "conditional_logic": 0,
                                "wrapper": {
                                    "width": 100,
                                    "class": "",
                                    "id": ""
                                },
                                "message": "",
                                "ui": 0,
                                "default_value": 0,
                                "min": 0,
                                "max": 0,
                                "rows_per_page": 20,
                                "layout": "table",
                                "button_label": "Add Row",
                                "collapsed": "",
                                "parent_repeater": "field_vgb0kd2ugwem8",
                                "acfe_repeater_stylised_button": 0,
                                "sub_fields": [
                                    {
                                        "key": "field_uqyfw6bgho5xm",
                                        "label": "Star",
                                        "name": "star",
                                        "aria-label": "",
                                        "type": "text",
                                        "instructions": "",
                                        "required": false,
                                        "conditional_logic": 0,
                                        "wrapper": {
                                            "width": 100,
                                            "class": "",
                                            "id": ""
                                        },
                                        "message": "",
                                        "ui": 0,
                                        "default_value": 0,
                                        "maxlength": "",
                                        "placeholder": "",
                                        "prepend": "",
                                        "append": "",
                                        "parent_repeater": "field_6jw9yal9sevnt"
                                    }
                                ]
                            }
                        ]
                    }
                ]
            }
        ],
        "location": [
            [
                {
                    "param": "page",
                    "operator": "==",
                    "value": "6"
                }
            ]
        ],
        "menu_order": 0,
        "position": "normal",
        "style": "default",
        "label_placement": "top",
        "instruction_placement": "label",
        "hide_on_screen": "",
        "active": true,
        "description": "",
        "show_in_rest": 0,
        "_valid": true
    }
]